[
  {
    "name": "Create Stage Instance",
    "method": "POST",
    "path": "/stage-instances",
    "params": [],
    "query": [],
    "description": "Creates a new Stage instance associated to a Stage channel.",
    "response": [
      {
        "partial": false,
        "optional": false,
        "nullable": false,
        "array": false,
        "reference": false,
        "value": [
          "snowflake"
        ],
        "name": "channel_id",
        "description": "The id of the Stage channel"
      },
      {
        "partial": false,
        "optional": false,
        "nullable": false,
        "array": false,
        "reference": false,
        "value": [
          "string"
        ],
        "name": "topic",
        "description": "The topic of the Stage instance (1-120 characters)"
      },
      {
        "partial": false,
        "optional": true,
        "nullable": false,
        "array": false,
        "reference": false,
        "value": [
          "integer"
        ],
        "name": "privacy_level",
        "description": "The [privacy level](#DOCS_RESOURCES_STAGE_INSTANCE/stage-instance-object-privacy-level) of the Stage instance (default GUILD_ONLY)"
      }
    ]
  },
  {
    "name": "Get Stage Instance",
    "method": "GET",
    "path": "/stage-instances/{channel.id}",
    "params": [
      {
        "name": "channel.id",
        "anchor": "channel-structure"
      }
    ],
    "query": [],
    "description": "Gets the stage instance associated with the Stage channel, if it exists.",
    "response": [
      {
        "partial": false,
        "optional": true,
        "nullable": false,
        "array": false,
        "reference": false,
        "value": [
          "string"
        ],
        "name": "topic",
        "description": "The topic of the Stage instance (1-120 characters)"
      },
      {
        "partial": false,
        "optional": true,
        "nullable": false,
        "array": false,
        "reference": false,
        "value": [
          "integer"
        ],
        "name": "privacy_level",
        "description": "The [privacy level](#DOCS_RESOURCES_STAGE_INSTANCE/stage-instance-object-privacy-level) of the Stage instance"
      }
    ]
  },
  {
    "name": "Delete Stage Instance",
    "method": "DELETE",
    "path": "/stage-instances/{channel.id}",
    "params": [
      {
        "name": "channel.id",
        "anchor": "channel-structure"
      }
    ],
    "query": [],
    "description": "Deletes the Stage instance."
  }
]